eitype/__init__.py
eitype/eitype.cpython-313-x86_64-linux-gnu.so
eitype-0.1.2.dist-info/METADATA
eitype-0.1.2.dist-info/WHEEL
eitype-0.1.2.dist-info/licenses/LICENSE
eitype.libs/libxkbcommon-de59cad2.so.0
eitype-0.1.2.dist-info/RECORD
